justrpc.py
setup.py
justrpc.egg-info/PKG-INFO
justrpc.egg-info/SOURCES.txt
justrpc.egg-info/dependency_links.txt
justrpc.egg-info/entry_points.txt
justrpc.egg-info/pbr.json
justrpc.egg-info/requires.txt
justrpc.egg-info/top_level.txt