Metadata-Version: 1.1
Name: justrpc
Version: 0.2.1
Summary: Fast and simple JSON RPC v1.0 for TCP connection
Home-page: http://github.com/mengzhuo/justrpc
Author: Meng Zhuo
Author-email: mengzhuo1203+justrpc@gmail.com
License: GPL2
Platform: any
Classifier: Development Status :: 3 - Alpha
Classifier: Intended Audience :: Developers
Classifier: License :: OSI Approved :: MIT License
Classifier: Programming Language :: Python :: 2.6
Classifier: Programming Language :: Python :: 2.7
